sr.comp.cli-1.12.0-py3.11-nspkg.pth
sr/comp/cli/__init__.py
sr/comp/cli/__main__.py
sr/comp/cli/add_delay.py
sr/comp/cli/awards.py
sr/comp/cli/command_line.py
sr/comp/cli/delay.py
sr/comp/cli/deploy.py
sr/comp/cli/fetch.py
sr/comp/cli/for_each_match.py
sr/comp/cli/knocked_out_teams.py
sr/comp/cli/league_scheduler.py
sr/comp/cli/lighting_controller.py
sr/comp/cli/list_midi_ports.py
sr/comp/cli/match_order_teams.py
sr/comp/cli/print_schedule.py
sr/comp/cli/schedule_league.py
sr/comp/cli/scorer.py
sr/comp/cli/shift_matches.py
sr/comp/cli/show_league_table.py
sr/comp/cli/show_schedule.py
sr/comp/cli/summary.py
sr/comp/cli/top_match_points.py
sr/comp/cli/update_layout.py
sr/comp/cli/validate.py
sr/comp/cli/yaml_round_trip.py
sr/comp/cli/youtube_chapters.py
sr/comp/cli/import_schedule/__init__.py
sr/comp/cli/import_schedule/core.py
sr/comp/cli/import_schedule/loading.py
sr/comp/cli/import_schedule/teams_mapping.py
sr/comp/cli/import_schedule/types.py
sr.comp.cli-1.12.0.dist-info/AUTHORS.rst
sr.comp.cli-1.12.0.dist-info/METADATA
sr.comp.cli-1.12.0.dist-info/WHEEL
sr.comp.cli-1.12.0.dist-info/entry_points.txt
sr.comp.cli-1.12.0.dist-info/namespace_packages.txt
sr.comp.cli-1.12.0.dist-info/top_level.txt
sr.comp.cli-1.12.0.dist-info/RECORD
